stackedup_helper_scripts/__init__.py
stackedup_helper_scripts/scripts/__init__.py
stackedup_helper_scripts/scripts/account_cost/__init__.py
stackedup_helper_scripts/scripts/account_cost/account_cost.py
stackedup_helper_scripts/scripts/cloudformation_update/__init__.py
stackedup_helper_scripts/scripts/cloudformation_update/cloudformation_update.py
stackedup_helper_scripts/scripts/cluster_lifecyclehook/__init__.py
stackedup_helper_scripts/scripts/cluster_lifecyclehook/cluster_lifecyclehook.py
stackedup_helper_scripts/scripts/deploy_notification/__init__.py
stackedup_helper_scripts/scripts/deploy_notification/deploy_notification.py
stackedup_helper_scripts/scripts/email_notification/__init__.py
stackedup_helper_scripts/scripts/email_notification/email_notification.py
stackedup_helper_scripts/scripts/force_deploy/__init__.py
stackedup_helper_scripts/scripts/force_deploy/force_deploy.py
stackedup_helper_scripts/scripts/instance_refresh/__init__.py
stackedup_helper_scripts/scripts/instance_refresh/instance_ami_refresh.py
stackedup_helper_scripts/scripts/instance_refresh/instance_ami_refresh_notification.py
stackedup_helper_scripts/scripts/instance_refresh/instance_refresh.py
stackedup_helper_scripts/scripts/instance_refresh/instance_refresh_notification.py
stackedup_helper_scripts/scripts/reset_task_notification/__init__.py
stackedup_helper_scripts/scripts/reset_task_notification/reset_task_notification.py
stackedup_helper_scripts/scripts/slack_notification/__init__.py
stackedup_helper_scripts/scripts/slack_notification/slack_notification.py
stackedup_helper_scripts/scripts/sns_relay/__init__.py
stackedup_helper_scripts/scripts/sns_relay/sns_relay.py
stackedup_helper_scripts/scripts/web_deploy/__init__.py
stackedup_helper_scripts/scripts/web_deploy/web_deploy.py
stackedup_helper_scripts/tasks/backup-parts/Dockerfile.remote
stackedup_helper_scripts/tasks/backup-parts/Makefile
stackedup_helper_scripts/tasks/backup-parts/README.md
stackedup_helper_scripts-0.0.17.dist-info/METADATA
stackedup_helper_scripts-0.0.17.dist-info/WHEEL
stackedup_helper_scripts-0.0.17.dist-info/licenses/LICENSE
stackedup_helper_scripts-0.0.17.dist-info/RECORD
