Metadata-Version: 2.4
Name: stackedup_helper_scripts
Version: 0.0.17
Summary: Tooling to help manage CloudFormation stacks
Project-URL: Homepage, https://github.com/ombu/stackedup-helper-scripts
Author-email: Martin Rio <martin@ombuweb.com>
License-File: LICENSE
Classifier: License :: OSI Approved :: MIT License
Classifier: Operating System :: OS Independent
Classifier: Programming Language :: Python :: 3
Requires-Python: >=3.9
